djc_core/__init__.py
djc_core/djc_core.cpython-310-aarch64-linux-gnu.so
djc_core/html_transformer/__init__.py
djc_core/html_transformer/__init__.pyi
djc_core/py.typed
djc_core/rust.py
djc_core/rust.pyi
djc_core/safe_eval/__init__.py
djc_core/safe_eval/error.py
djc_core/safe_eval/eval.py
djc_core/safe_eval/sandbox.py
djc_core/template_parser/__init__.py
djc_core/template_parser/compile.py
djc_core/template_parser/parse.py
djc_core-1.3.0.dist-info/METADATA
djc_core-1.3.0.dist-info/WHEEL
djc_core-1.3.0.dist-info/licenses/LICENSE
djc_core-1.3.0.dist-info/RECORD
