Metadata-Version: 2.4
Name: djc_core
Version: 1.3.0
Classifier: Programming Language :: Python
Classifier: Programming Language :: Python :: 3
Classifier: Programming Language :: Python :: 3.10
Classifier: Programming Language :: Python :: 3.11
Classifier: Programming Language :: Python :: 3.12
Classifier: Programming Language :: Python :: 3.13
Classifier: Programming Language :: Python :: 3.14
Classifier: Programming Language :: Rust
Classifier: Programming Language :: Python :: Implementation :: CPython
Classifier: Programming Language :: Python :: Implementation :: PyPy
License-File: LICENSE
Summary: Core library for django-components written in Rust.
Keywords: django,components,html
Author-email: Juro Oravec <juraj.oravec.josefson@gmail.com>
License: MIT
Requires-Python: >=3.10, <4.0
Project-URL: Changelog, https://github.com/django-components/djc-core/blob/main/CHANGELOG.md
Project-URL: Donate, https://github.com/sponsors/EmilStenstrom
Project-URL: Homepage, https://github.com/django-components/djc-core/
Project-URL: Issues, https://github.com/django-components/djc-core/issues
